research_tools/__init__.py
research_tools/__main__.py
research_tools/config.py
research_tools/py.typed
research_tools/cli/__init__.py
research_tools/cli/cache.py
research_tools/cli/common.py
research_tools/cli/main.py
research_tools/clients/__init__.py
research_tools/clients/hackernews.py
research_tools/clients/openai.py
research_tools/clients/perplexity.py
research_tools/clients/searchapi.py
research_tools/clients/serper.py
research_tools/db/__init__.py
research_tools/db/connection.py
research_tools/db/models/__init__.py
research_tools/db/models/cache.py
research_tools/db/repositories/__init__.py
research_tools/db/repositories/base.py
research_tools/db/repositories/cache.py
research_tools/mcp/__init__.py
research_tools/mcp/server.py
research_tools/models/__init__.py
research_tools/models/ads_transparency.py
research_tools/models/ai_mode.py
research_tools/models/articles.py
research_tools/models/competitor.py
research_tools/models/hackernews.py
research_tools/models/llm_tracking.py
research_tools/models/news.py
research_tools/models/rank_tracking.py
research_tools/models/search.py
research_tools/models/social.py
research_tools/models/trends.py
research_tools/models/video.py
research_tools/registry/__init__.py
research_tools/registry/factory.py
research_tools/registry/params.py
research_tools/registry/renderer.py
research_tools/registry/sections.py
research_tools/registry/tool.py
research_tools/services/__init__.py
research_tools/services/ads_transparency.py
research_tools/services/ai_mode.py
research_tools/services/base.py
research_tools/services/cache.py
research_tools/services/competitor.py
research_tools/services/devto.py
research_tools/services/google.py
research_tools/services/hackernews.py
research_tools/services/llm_tracking.py
research_tools/services/news.py
research_tools/services/rank_tracking.py
research_tools/services/reddit.py
research_tools/services/trends.py
research_tools/services/youtube.py
research_tools/tools/__init__.py
mcp_cli_research_tools-0.2.2.dist-info/METADATA
mcp_cli_research_tools-0.2.2.dist-info/WHEEL
mcp_cli_research_tools-0.2.2.dist-info/entry_points.txt
mcp_cli_research_tools-0.2.2.dist-info/licenses/LICENSE
mcp_cli_research_tools-0.2.2.dist-info/RECORD
