Metadata-Version: 2.4
Name: mcp-cli-research-tools
Version: 0.2.2
Summary: CLI + MCP server for dev.to, Google, Reddit, YouTube, Trends, News, Hacker News, and SearchAPI research
Author-email: halilc4 <halilc4@gmail.com>
License-File: LICENSE
Requires-Python: >=3.11
Requires-Dist: cyclopts>=3.0.0
Requires-Dist: httpx>=0.27.0
Requires-Dist: python-dotenv>=1.0.0
Requires-Dist: rich>=13.0.0
Requires-Dist: sqlmodel>=0.0.22
Provides-Extra: mcp
Requires-Dist: fastmcp>=2.0.0; extra == 'mcp'
